ansys/api/speos/bsdf/v1/anisotropic_bsdf_pb2.py
ansys/api/speos/bsdf/v1/anisotropic_bsdf_pb2_grpc.py
ansys/api/speos/bsdf/v1/bsdf_creation_pb2.py
ansys/api/speos/bsdf/v1/bsdf_creation_pb2_grpc.py
ansys/api/speos/bsdf/v1/spectral_bsdf_pb2.py
ansys/api/speos/bsdf/v1/spectral_bsdf_pb2_grpc.py
ansys/api/speos/lpf/v1/lpf_file_reader_pb2.py
ansys/api/speos/lpf/v1/lpf_file_reader_pb2_grpc.py
ansys/api/speos/xmp/v1/xmp_file_pb2.py
ansys/api/speos/xmp/v1/xmp_file_pb2_grpc.py
ansys_optics_grpcapi-3.0.0.dist-info/METADATA
ansys_optics_grpcapi-3.0.0.dist-info/WHEEL
ansys_optics_grpcapi-3.0.0.dist-info/top_level.txt
ansys_optics_grpcapi-3.0.0.dist-info/RECORD
