Metadata-Version: 2.1
Name: ansys-optics-grpcapi
Version: 3.0.0
Summary: Protocol Buffer structure for Speos
Home-page: https://tfs.ansys.com:8443/tfs/ANSYS_Development/OPTIS_SPEOS/_git/SpeosProto
Author: Ansys Inc.
Author-email: support@ansys.com
License: (c) 2022 ANSYS, Inc. Unauthorized use, distribution, or duplication is prohibited.
Platform: UNKNOWN
Requires-Python: >=3.5
Requires-Dist: grpcio-tools
